{
  "name": "Mabel Barrett",
  "age": 24,
  "address": {
    "street": "Vegupo Center",
    "city": "Roreben",
    "state": "WV",
    "zip": "59222"
  },
  "contact": {
    "phone": "(721) 962-4421",
    "servicePhone": "800275549"
  },
  "birthday": "2006-08-22T06:42:24.877Z",
  "ip": "83.106.211.58",
  "foo": "bar",
  "profile": {
    "about": "Vonus ziseg ozgo belimsor zagabhis ri zufpu hirta ek ta guwac vocu ar repil. Jih malka pa ba hodmojma rakfi bikaf av datcizi is muufi wakuk. Uhkecre hokbekci on je peh ippebe saja giri kavzor befumpa mivgoz zicre lawufpom galupfo echo. Nu upucitej udpivdat semib ha ohgucvu mowap ikcugdil wur ku du ap. Ivko lub giivu ata tun ilki civvobjar nijfe sarzakem pu jocecorop inego ogte.",
    "bio": "Dojrih zekirvek emvin ebudon zo jikfav jom popete hopjufena ruz ifhun sipfag. Wotroep jirhu sik zodcerego vijohavi das idu el oc fu urnobes lol hepvob. Lu geli ju upzewu do forooh lag fata bo dak ezaametuc efraderi juj lejipes. Tuiridow kaw ufaweh zano ad fevhumizu vovnu meiz zulahnin kotkekaz ti hitozu po lamhegoju gi. Gov ire pirol ret jawku jotbogwul peizi usiveub wuplor fenac je ribuav da mojuwone zisikozo lulanlaz palo muczip. Wil zevek liteznuh lekib tom ressah nab bic himwacce mevonok zaif popnaw lecioju kin ket. Jut dilcifa seunugu repku ludirilo veb sad eju pitvokfot wib palepos suwezoje kotasca hogmoul oja linil."
  },
  "apiKey": "61f6234cf8bfe191ca8e133a416a693a73f45880b9257ad5ba28c390d43ccf2b",
  "currency": {
    "code": "BAM",
    "name": "Bosnia and Herzegovina Convertible Marka"
  }
}