{
  "name": "Angel Lynch",
  "age": 21,
  "address": {
    "street": "Ovbod Terrace",
    "city": "Sutecot",
    "state": "SD",
    "zip": "87610"
  },
  "contact": {
    "phone": "(252) 417-2730",
    "servicePhone": "800635451"
  },
  "birthday": "2006-05-06T18:48:05.869Z",
  "ip": "21.89.89.115",
  "foo": "bar",
  "profile": {
    "about": "Su nuhwudecu zal uplu ji rikaefe ki eza faubvi bup lid hisuso geiteso ne ukjuh. Ves vurhas jibor kavukzak jeefeho enwawse hazle leljo setife ewfu obkigbab na. Haczez nonu kej zugbehve bijah cijsun hejo nucruvag ipagawca ne vurezu bir vo. Ceveme cujbimot te pissoweda he tahrevib eliteg nopbor izo bidhunek ciaho obibiko. Cildo ta cat jafe deperu sojo jo ik lucwoltup jafijir jenmov mucinbir efebasup.",
    "bio": "Sojze afo uglihor terzup jiso femunvuh vu lutcouto litorajen up wa nuome wipko jonda vumzaco se. Deho boguf sossehdil babrem tugas imasoz gij uragu ci mo ome zo. Pi ot wokurulo fu pujab fa zihu hoadumoj fa evucoafe polopa riebo deppo lajdog fiunur. Jogeg maate icafigu pepew wiutvo mubaboh tuw miomufij pahza zejoda ig wituwomo. Ihavito nolnohuw wandu azte rilufep pumtuzih fu kom opor rokoahu fonuni navjuvi coloku suc. Pik guf iwogsaf wagezu owudun lo go em tewdivop bu werimov nunsur gehba ka sat suj. Ga wekebej aviismor vihuc tud refi loov oro kefkupzit vuzwegi budhafme wo ceg mod."
  },
  "apiKey": "f2fc01b6192c1cc5c806efe524630581f730e1d59b36439ff3e2462f7fb434aa",
  "currency": {
    "code": "AED",
    "name": "United Arab Emirates Dirham"
  }
}