{
  "name": "Garrett Poole",
  "age": 20,
  "address": {
    "street": "Vuwvef Park",
    "city": "Bufgabeb",
    "state": "WI",
    "zip": "73322"
  },
  "contact": {
    "phone": "(804) 237-1065",
    "servicePhone": "800679187"
  },
  "birthday": "1991-02-04T02:08:23.843Z",
  "ip": "183.245.84.128",
  "foo": "bar",
  "profile": {
    "about": "Nuz lem sud isomoace etafu gefo oz cijan opusahbo markimje ohafewe gi. Naggevi jiuznap da vo okni rica fiz rohezher cizzofkak riwveku dekda sucejkoc micwoz ewbokjod vum dekalgil. Za uhhot ifoij cozud wahhajmoz izece nuokno huusgo reeve cuddu igi iw sef.",
    "bio": "Tena malwog dusosiga edpe duaral vocjifal vitradak ijjil ucokef memcawna iri ote pa varow niwul va teralasi. Hasber tapa jeg dutupav eca avifez rubopi ar zocna du anu ripnan. Jucponeb fissip itudoki taf misar pumjoj ahko oka hungapgu zitakso zejzajif wapjop nadwu."
  },
  "apiKey": "d756346be36e33479dcfd47505d3e4404d1ebdd0035c10b77ff73969cc8c8aca",
  "currency": {
    "code": "DJF",
    "name": "Djibouti Franc"
  }
}