{
  "name": "Derrick Ford",
  "age": 38,
  "address": {
    "street": "Ahre Loop",
    "city": "Jowemjit",
    "state": "KY",
    "zip": "55845"
  },
  "contact": {
    "phone": "(588) 221-5357",
    "servicePhone": "800969834"
  },
  "birthday": "2001-06-30T08:14:31.375Z",
  "ip": "73.101.121.99",
  "foo": "bar",
  "profile": {
    "about": "Uhoizicof vine oderolef hotis tobezki li hosif bor gipa erfemumi akhutjo mipuzu bu hejetew. Etzol zefuci duge fu waecagas ses nar fe hafjikjez dawzen kebeino huluir hokoc vitjif ga bevgapze eha. Ziif liwge mi juhgo leobe adi buf ez datafab gemfode icu jarbaw ivo apzij. Mimpi mozpo nakopla ogkovaw pi pok la ka zobmi ji eh usa hi. Hakana neegube lustumeh muhe guptuh epa joiccur amahog tejo wag nidokad be gefemmej dudo wop moho. Totudu ofbuzif fediclip megogiju ijivermej jestedid cajorpe piguva vihigvi mupifih bosujowu kod ohpe rutdenpa otpoc lemfawpoj al.",
    "bio": "Jongo izo ub fomwarru bu hosgeh cuil sowtezvec jiznedpul ce pa ta febot mi. Ufini canrami codawa sop rowca odafuaru pu ralo adigepo owjodic vegedejo re gegugasa bodenisa batomow kipuldek. Kubnen takmucu rin duwsub semko kejufa hinpaeb imher ezaluc zacrufboh ikowi rolo lioh. Zonafu na jol awe oma sovdab rogla tibuj ri icfic ali dugeabe dalhu fofedivud. Ce unamoc fa usa wuitane nonkezigi ij zafa sone asiko kivujtuj jurtavak affo arneg pomewho jenu. Diz ti po wivogiget divjej avmil moklahu lo levpaj jibumi epiektoz owaniveke bamtepgow fervico. Hi ijcobwom vu fidmaspeh neupjer gasazil necuf lokigje zuckigjas wazlup megdejla lil madauc izjez uzo ganbuk tol."
  },
  "apiKey": "2a098af4a12fb473e04bcc97d08ca25b400316b4cedb19c6a6b3437aa4ab20be",
  "currency": {
    "code": "SBD",
    "name": "Solomon Islands Dollar"
  }
}